<?xml version="1.0" encoding="utf-8" ?>
<Defs>

  <ThingDef ParentName="RE_IngestibleHerbs">
    <defName>RE_MedicineRed</defName>
    <label>red herb (powder)</label>
    <description>Powder extracted from the Red Herb. Provides no benefits alone. Can be mixed with other herbs.</description>
    <graphicData>
      <texPath>Things/Item/Resource/Herbs/RedPowder</texPath>
      <graphicClass>Graphic_Single</graphicClass>
      <drawSize>0.85</drawSize>
    </graphicData>
		<techLevel>Neolithic</techLevel>
		<statBases>
      <MarketValue>10</MarketValue>
      <Mass>0.35</Mass>
      <Flammability>1.3</Flammability>
      <DeteriorationRate>6</DeteriorationRate>
    </statBases>
    <tickerType>Rare</tickerType>
    <recipeMaker>
			<recipeUsers>
        <li>CraftingSpot</li>
        <li>DrugLab</li>
      </recipeUsers>
      <workSpeedStat>DrugCookingSpeed</workSpeedStat>
      <workSkill>Cooking</workSkill>
    </recipeMaker>
    <costList>
      <RE_Plant_ResidentEvilHerbRed>1</RE_Plant_ResidentEvilHerbRed>
    </costList>
    <comps>
      <li Class="CompProperties_Rottable">
        <daysToRotStart>150</daysToRotStart>
				<rotDestroys>true</rotDestroys>
			</li>
    </comps>
  </ThingDef>

</Defs>